{
  "name": "GeoJSON",
  "abstract": "A GeoJSON object",
  "status": "stable",
  "dateTimeAddition": "2023-05-24T14:56:51+00:00",
  "itemClass": "schema",
  "register": "ogc-building-block-register",
  "version": "1.0",
  "dateOfLastChange": "2023-05-15",
  "sources": [
    {
      "title": "IETF RFC 7946 - The GeoJSON Format",
      "link": "https://datatracker.ietf.org/doc/html/rfc7946"
    }
  ],
  "schema": "https://geojson.org/schema/Feature.json",
  "ldContext": "https://geojson.org/geojson-ld/geojson-context.jsonld",
  "maturity": "mature",
  "scope": "geo",
  "group": "Common"
}
